tester/__init__.py
tester/__main__.py
tester/config.py
tester/io.py
tester/runner.py
naive_tester-1.2.1.dist-info/LICENSE
naive_tester-1.2.1.dist-info/METADATA
naive_tester-1.2.1.dist-info/WHEEL
naive_tester-1.2.1.dist-info/entry_points.txt
naive_tester-1.2.1.dist-info/top_level.txt
naive_tester-1.2.1.dist-info/RECORD
