Metadata-Version: 2.1
Name: naive-tester
Version: 1.2.1
Summary: A simple testing system based on files
Home-page: https://github.com/FilippSolovev/naive-tester
Author: Filipp Solovev
Author-email: solovyev.filipp@gmail.com
License: MIT
Platform: UNKNOWN
Classifier: License :: OSI Approved :: MIT License
Classifier: Programming Language :: Python :: 3
Classifier: Programming Language :: Python :: 3.6
Classifier: Operating System :: OS Independent
Requires-Python: >=3.6
